pop_sort/__init__.py
pop_sort/bubble_sort.py
pop_sort/bucket_sort.py
pop_sort/decorators.py
pop_sort/insertion_sort.py
pop_sort/merge_sort.py
pop_sort/quick_sort.py
pop_sort/selection_sort.py
tests/__init__.py
tests/test_sort.py
pop_sort-1.0.1.dist-info/LICENSE
pop_sort-1.0.1.dist-info/METADATA
pop_sort-1.0.1.dist-info/WHEEL
pop_sort-1.0.1.dist-info/top_level.txt
pop_sort-1.0.1.dist-info/RECORD
