Metadata-Version: 2.1
Name: pop-sort
Version: 1.0.1
Summary: Project for exploring popular sorting algorithms.
Home-page: https://github.com/MartynasGr/pop_sort
Author: Martynas Greičius
Author-email: martynas.greicius@gmail.com
License: MIT
Classifier: Programming Language :: Python :: 3
Classifier: License :: OSI Approved :: MIT License
Classifier: Operating System :: OS Independent
Requires-Python: >=3.10
License-File: LICENSE
